pmdatapipelinelight/__init__.py
pmdatapipelinelight/pmaws.py
pmdatapipelinelight/pmcore.py
pmdatapipelinelight/pmmatillion.py
pmdatapipelinelight/pmtransfer.py
pmdatapipelineslight/__init__.py
pmdatapipelineslight/pmaws.py
pmdatapipelineslight/pmcore.py
pmdatapipelineslight/pmmatillion.py
pmdatapipelineslight/pmtransfer.py
pmdatapipelineslight-0.0.3.dist-info/LICENSE
pmdatapipelineslight-0.0.3.dist-info/METADATA
pmdatapipelineslight-0.0.3.dist-info/WHEEL
pmdatapipelineslight-0.0.3.dist-info/top_level.txt
pmdatapipelineslight-0.0.3.dist-info/RECORD
